stocksurferbd/__init__.py
stocksurferbd/fundamental_data_scraper.py
stocksurferbd/price_data_scraper.py
stocksurferbd/price_plots.py
stocksurferbd-0.1.3.dist-info/METADATA
stocksurferbd-0.1.3.dist-info/WHEEL
stocksurferbd-0.1.3.dist-info/top_level.txt
stocksurferbd-0.1.3.dist-info/RECORD
