Metadata-Version: 2.1
Name: stocksurferbd
Version: 0.1.3
Summary: A Python library for downloading stock market data of Dhaka Stock Exchange(DSE) and Chittagong Stock Exchange(CSE).
Home-page: https://github.com/skfarhad/stocksurferbd
Author: Sk Farhad
Author-email: sk.farhad.eee@gmail.com
Project-URL: Bug Tracker, https://github.com/skfarhad/stocksurferbd/issues
Classifier: Programming Language :: Python :: 3
Classifier: License :: OSI Approved :: MIT License
Classifier: Operating System :: OS Independent
Requires-Python: >=3.10
Requires-Dist: requests ==2.32.3
Requires-Dist: pandas ==2.2.2
Requires-Dist: openpyxl ==3.1.5
Requires-Dist: beautifulsoup4 ==4.9.3
Requires-Dist: matplotlib ==3.9.2
Requires-Dist: mplfinance ==0.12.10b0
Requires-Dist: pyti ==0.2.2
Requires-Dist: tapy ==1.9.1
